hueforge/__init__.py
hueforge/utility.py
hueforge/algorithms/__init__.py
hueforge/algorithms/colorblindness.py
hueforge/algorithms/other.py
hueforge/algorithms/property_adjustment.py
hueforge/color/__init__.py
hueforge/color/color.py
hueforge/color/convertor.py
hueforge/color/detection.py
hueforge-1.32.dist-info/METADATA
hueforge-1.32.dist-info/WHEEL
hueforge-1.32.dist-info/top_level.txt
hueforge-1.32.dist-info/RECORD
