Metadata-Version: 2.1
Name: hueforge
Version: 1.32
Summary: Python color engine.
Author: Schkimansky
Author-email: <ahmadchawla1432@gmail.com>
Keywords: python,color,engine,colorengine,hue,contrast,saturation,hueforge,manager
Classifier: Development Status :: 5 - Production/Stable
Classifier: Intended Audience :: Developers
Classifier: Programming Language :: Python :: 3
Classifier: Operating System :: Unix
Classifier: Operating System :: MacOS :: MacOS X
Classifier: Operating System :: Microsoft :: Windows
